pyvmote/__init__.py
pyvmote/core.py
pyvmote/graph_generator.py
pyvmote/service.py
pyvmote/static/css/style.css
pyvmote/static/dinamics/preview.js
pyvmote/static/dinamics/script.js
pyvmote/templates/index.html
pyvmote/templates/preview.html
pyvmote-1.0.0.dist-info/METADATA
pyvmote-1.0.0.dist-info/WHEEL
pyvmote-1.0.0.dist-info/top_level.txt
pyvmote-1.0.0.dist-info/RECORD
