Metadata-Version: 2.4
Name: pyvmote
Version: 1.0.0
Summary: Librería para generar gráficos y visualizar imágenes en tiempo real en remoto
Author: Juan Grima Sanchez
Author-email: Juan Grima Sanchez <juan.grimasanchez5@gmail.com>
License: MIT
Classifier: Programming Language :: Python :: 3
Classifier: Operating System :: OS Independent
Requires-Python: >=3.7
Requires-Dist: fastapi
Requires-Dist: uvicorn[standard]
Requires-Dist: jinja2
Requires-Dist: matplotlib
Requires-Dist: mpld3
Requires-Dist: scipy
Requires-Dist: numpy
Requires-Dist: pandas
Dynamic: author
